bgclspserver/__init__.py
bgclspserver/__main__.py
bgclspserver/server.py
bgclspserver/cst/__init__.py
bgclspserver/cst/diagnostic_listener.py
bgclspserver/cst/symbol_table_visitor.py
bgclspserver/filewriter/__init__.py
bgclspserver/filewriter/jinja-templates/__init__.py
bgclspserver/gen/python/BgcDsl/BgcDslLexer.py
bgclspserver/gen/python/BgcDsl/BgcDslListener.py
bgclspserver/gen/python/BgcDsl/BgcDslParser.py
bgclspserver/gen/python/BgcDsl/BgcDslVisitor.py
bgclspserver/symboltable/__init__.py
bgclspserver/symboltable/symbol_table.py
bgclspserver/utils/__init__.py
bgclspserver/utils/bgc_errors_strategy.py
bgclspserver/utils/compute_token_index.py
bgclspserver/utils/suggest_variables.py
tests/__init__.py
tests/__main__zum_testen.py
tests/test_symbolTableVisitor.py
BGC_Language_Server-0.40.0.dist-info/LICENSE.txt
BGC_Language_Server-0.40.0.dist-info/METADATA
BGC_Language_Server-0.40.0.dist-info/WHEEL
BGC_Language_Server-0.40.0.dist-info/entry_points.txt
BGC_Language_Server-0.40.0.dist-info/top_level.txt
BGC_Language_Server-0.40.0.dist-info/RECORD
